pytorch360convert/__init__.py
pytorch360convert/pytorch360convert.py
pytorch360convert/version.py
pytorch360convert-0.2.3.dist-info/licenses/LICENSE
pytorch360convert-0.2.3.dist-info/METADATA
pytorch360convert-0.2.3.dist-info/WHEEL
pytorch360convert-0.2.3.dist-info/top_level.txt
pytorch360convert-0.2.3.dist-info/RECORD
